Metadata-Version: 2.1
Name: SwanLake
Version: 0.0.0
Summary: swan-lake
